LICENSE
MANIFEST.in
README.md
scrapy.cfg
setup.cfg
setup.py
os_scrapy_record/__init__.py
os_scrapy_record/const.py
os_scrapy_record/exceptions.py
os_scrapy_record/extensions.py
os_scrapy_record/fetch_status.py
os_scrapy_record/items.py
os_scrapy_record/middlewares.py
os_scrapy_record/pipelines.py
os_scrapy_record/settings.py
os_scrapy_record/utils.py
os_scrapy_record.egg-info/PKG-INFO
os_scrapy_record.egg-info/SOURCES.txt
os_scrapy_record.egg-info/dependency_links.txt
os_scrapy_record.egg-info/not-zip-safe
os_scrapy_record.egg-info/requires.txt
os_scrapy_record.egg-info/top_level.txt
os_scrapy_record/spiders/__init__.py
requirements/requirements-lint.txt
requirements/requirements-test.txt
requirements/requirements.txt
tests/__init__.py
tests/test_scrapy_check.py